data_explorer_qt/__init__.py
data_explorer_qt/dataexplorer.py
data_explorer_qt/dataexplorerGUI.py
data_explorer_qt/guihelper.py
data_explorer_qt/setqtapi.py
data_explorer_qt/__pycache__/__init__.cpython-313.pyc
data_explorer_qt/__pycache__/dataexplorer.cpython-313.pyc
data_explorer_qt/__pycache__/dataexplorerGUI.cpython-313.pyc
data_explorer_qt/__pycache__/guihelper.cpython-313.pyc
data_explorer_qt/__pycache__/setqtapi.cpython-313.pyc
data_explorer_qt/config/__init__.py
data_explorer_qt/config/config.toml
data_explorer_qt/config/readconfig.py
data_explorer_qt/config/__pycache__/__init__.cpython-311.pyc
data_explorer_qt/config/__pycache__/__init__.cpython-313.pyc
data_explorer_qt/config/__pycache__/readconfig.cpython-311.pyc
data_explorer_qt/config/__pycache__/readconfig.cpython-313.pyc
data_explorer_qt/config/__pycache__/readsettings.cpython-313.pyc
data_explorer_qt/data/__init__.py
data_explorer_qt/data/base.py
data_explorer_qt/data/datamodel.py
data_explorer_qt/data/filterwidget.py
data_explorer_qt/data/importexportGUI.py
data_explorer_qt/data/numcatwidget.py
data_explorer_qt/data/tableGUI.py
data_explorer_qt/data/__pycache__/__init__.cpython-311.pyc
data_explorer_qt/data/__pycache__/__init__.cpython-313.pyc
data_explorer_qt/data/__pycache__/base.cpython-313.pyc
data_explorer_qt/data/__pycache__/dataenums.cpython-311.pyc
data_explorer_qt/data/__pycache__/dataenums.cpython-313.pyc
data_explorer_qt/data/__pycache__/datamodel.cpython-311.pyc
data_explorer_qt/data/__pycache__/datamodel.cpython-313.pyc
data_explorer_qt/data/__pycache__/filterwidget.cpython-311.pyc
data_explorer_qt/data/__pycache__/filterwidget.cpython-313.pyc
data_explorer_qt/data/__pycache__/importexportGUI.cpython-311.pyc
data_explorer_qt/data/__pycache__/importexportGUI.cpython-313.pyc
data_explorer_qt/data/__pycache__/numcatwidget.cpython-313.pyc
data_explorer_qt/data/__pycache__/tableGUI.cpython-311.pyc
data_explorer_qt/data/__pycache__/tableGUI.cpython-313.pyc
data_explorer_qt-0.1.11.dist-info/licenses/LICENSE
data_explorer_qt-0.1.11.dist-info/METADATA
data_explorer_qt-0.1.11.dist-info/WHEEL
data_explorer_qt-0.1.11.dist-info/entry_points.txt
data_explorer_qt-0.1.11.dist-info/top_level.txt
data_explorer_qt-0.1.11.dist-info/RECORD
