Metadata-Version: 2.4
Name: data-explorer-qt
Version: 0.1.11
Author-email: Uddhava Swaminathan <karrablaster123@proton.me>
License:                     GNU GENERAL PUBLIC LICENSE
Project-URL: Homepage, https://github.com/karrablaster123/data-explorer-qt
Project-URL: Issues, https://github.com/karrablaster123/data-explorer-qt/issues
Requires-Python: >=3.12
License-File: LICENSE
Requires-Dist: pandas>=2.2
Requires-Dist: toml
Requires-Dist: PySide6>=6.9
Requires-Dist: superqt
Requires-Dist: python-calamine>=0.2
Requires-Dist: openpyxl>=3.1
Requires-Dist: seaborn>=0.13.2
Requires-Dist: matplotlib>=3.9.2
Requires-Dist: PySideSix-Frameless-Window>=0.7
Requires-Dist: pyarrow
Requires-Dist: statsmodels>=0.14
Dynamic: license-file
